fatafat/__init__.py
fatafat/blog.py
fatafat/util.py
fatafat/templates/config.jinja2
fatafat/templates/README.md.jinja2
fatafat/themes/simi/.DS_Store
fatafat/themes/simi/assets/css/styles.css
fatafat/themes/simi/templates/archives.jinja2
fatafat/themes/simi/templates/article.jinja2
fatafat/themes/simi/templates/base.jinja2
fatafat/themes/simi/templates/disqus_script.jinja2
fatafat/themes/simi/templates/footer.jinja2
fatafat/themes/simi/templates/index.jinja2
fatafat-0.0.2.dist-info/DESCRIPTION.rst
fatafat-0.0.2.dist-info/entry_points.txt
fatafat-0.0.2.dist-info/METADATA
fatafat-0.0.2.dist-info/metadata.json
fatafat-0.0.2.dist-info/RECORD
fatafat-0.0.2.dist-info/top_level.txt
fatafat-0.0.2.dist-info/WHEEL
