Metadata-Version: 2.0
Name: fatafat
Version: 0.0.2
Summary: A static blog generator and an offline blogging tool.
Home-page: http://github.com/isubuz/fatafat
Author: Subhajit Ghosh
Author-email: i.subhajit.ghosh@gmail.com
License: UNKNOWN
Platform: UNKNOWN
Classifier: Development Status :: 2 - Pre-Alpha
Classifier: Intended Audience :: Developers
Classifier: Environment :: Console
Classifier: License :: OSI Approved :: Apache Software License
Classifier: Operating System :: MacOS :: MacOS X
Classifier: Programming Language :: Python :: 2.7
Classifier: Programming Language :: Python :: 3.4
Classifier: Topic :: Internet :: WWW/HTTP
Classifier: Topic :: Software Development :: Libraries :: Python Modules
Requires-Dist: markdown (>=2.4)
Requires-Dist: jinja2 (>=2.7)
Requires-Dist: sh (>=1.09)
Requires-Dist: six
